voxelium/__init__.py
voxelium/base/__init__.py
voxelium/base/args.py
voxelium/base/ctf.py
voxelium/base/ctf_estimation.py
voxelium/base/explicit_grid_utils.py
voxelium/base/grid.py
voxelium/base/grid_rotations.py
voxelium/base/io_logger.py
voxelium/base/model_container.py
voxelium/base/plot.py
voxelium/base/single_particle_dataset.py
voxelium/base/single_particle_validation_sampler.py
voxelium/base/so3.py
voxelium/base/spectral.py
voxelium/base/star_file.py
voxelium/base/subtomo_validation_sampler.py
voxelium/base/test.py
voxelium/base/torch_utils.py
voxelium/relion/__init__.py
voxelium/relion/dataset.py
voxelium/relion/so3.py
voxelium/relion/utils.py
voxelium/torch_extensions/__init__.py
voxelium/torch_extensions/inplace_topk/_C.cpython-39-x86_64-linux-gnu.so
voxelium/torch_extensions/inplace_topk/__init__.py
voxelium/torch_extensions/inplace_topk/inplace_topk.cpp
voxelium/torch_extensions/inplace_topk/inplace_topk.py
voxelium/torch_extensions/inplace_topk/inplace_topk_cpu_kernels.cpp
voxelium/torch_extensions/inplace_topk/inplace_topk_cuda_kernels.cu
voxelium/torch_extensions/inplace_topk/pybind.cpp
voxelium/torch_extensions/inplace_topk/test_inplace_topk.py
voxelium/torch_extensions/sparse3d/_C.cpython-39-x86_64-linux-gnu.so
voxelium/torch_extensions/sparse3d/__init__.py
voxelium/torch_extensions/sparse3d/projector.py
voxelium/torch_extensions/sparse3d/pybind.cpp
voxelium/torch_extensions/sparse3d/reconstruction_layer.py
voxelium/torch_extensions/sparse3d/test_sparse3d.py
voxelium/torch_extensions/sparse3d/trilinear_projection.cpp
voxelium/torch_extensions/sparse3d/trilinear_projection.py
voxelium/torch_extensions/sparse3d/trilinear_projection_cpu_backward_kernel.cpp
voxelium/torch_extensions/sparse3d/trilinear_projection_cpu_forward_kernel.cpp
voxelium/torch_extensions/sparse3d/trilinear_projection_cuda_backward_kernel.cu
voxelium/torch_extensions/sparse3d/trilinear_projection_cuda_forward_kernel.cu
voxelium-0.0.5.dist-info/METADATA
voxelium-0.0.5.dist-info/WHEEL
voxelium-0.0.5.dist-info/top_level.txt
voxelium-0.0.5.dist-info/RECORD
voxelium-0.0.5.dist-info/sboms/auditwheel.cdx.json
