Metadata-Version: 2.4
Name: Voxelium
Version: 0.0.5
Summary: Voxelium - a powerful tool for volumetric processing with CUDA support.
Author-email: Dari Kimanius <dari.kimanius@czii.org>
License: GPL-2.0-or-later
Keywords: CryoEM,CryoET,Reconstruction,ML
Requires-Python: >=3.9
Requires-Dist: torch==2.6.0
Requires-Dist: torchvision==0.21.0
Requires-Dist: loguru
Requires-Dist: matplotlib
Requires-Dist: mrcfile
Requires-Dist: numpy==1.*
Requires-Dist: vtk
Requires-Dist: scikit-learn
Requires-Dist: scipy
Requires-Dist: tensorboard
Requires-Dist: tqdm
Requires-Dist: starfile
Requires-Dist: umap-learn
Requires-Dist: imageio
Requires-Dist: msgpack
Requires-Dist: healpy
Provides-Extra: test
Requires-Dist: pytest; extra == "test"
